{
  "number": "15º",
  "date": "07/12/2020",
  "description": "15º de Capitán Sarmiento",
  "link": "/bulletins/4602",
  "status": "completed",
  "fullText": "\n[DOC 1]\nBoletines/Capitán Sarmiento\nDecreto Nº1068/20\nDecreto Nº 1068/20\nCapitán Sarmiento, 27/11/2020\nVisto\nLa Ordenanza Nro. 2667/2020; y\nConsiderando\nque  por la Ordenanza mencionada se establece el Reglamento del Régimen de los Concursos para el Acceso al Empleo Público de la Municipalidad de Capitán Sarmiento, el cual forma parte integrante de la presente como Anexo I.-\nPor todo ello, en uso de las facultades que me son propias;\nD E C R E T O\nARTICULO 1ro.:\nTéngase por Ordenanza del Municipio.-\nARTICULO 2do.:\nEl presente Decreto será refrendado por la Secretaria General de Gobierno y el Secretario de Hacienda y Finanzas.-\nARTICULO 3ro.:\nComuníquese, Publíquese, Regístrese y Cumplido, Archívese.-\nFIRMADO:        ING. JAVIER IGUACEL                        = INTENDENTE MUNICIPAL\nFERNANDA ASTORINO HURTADO     = SEC.\nGRAL. DE GOBIERNO\nFRANCISCO PIGRETTI                        = SEC. DE HACIENDA Y FINANZAS\nAnexos\nanexo I\nreglamentacion del regimen concurso empleo publico municipal\nDESCARGAR\n\n[DOC 2]\nBoletines/Capitán Sarmiento\nDecreto Nº1071/2020\nDecreto Nº 1071/2020\nCapitán Sarmiento, 27/11/2020\nVisto\nLa Ordenanza Nº 2667/2020 que reglamenta el Régimen de los Concursos Públicos Generales de la Municipalidad de Capitán Sarmiento; y\nConsiderando\nQue el Departamento Ejecutivo ha solicitado el llamado a Concurso Publico General y para cubrir ocho (8) cargos de la Planta Permanente, a saber: cinco (5)  Personal Obrero, uno (1)  Personal de  Servicio,  y dos (2) Personal de Administración;\nQue dichos ingresos serán cubiertos mediante la apertura de un concurso donde los postulantes reúnan las condiciones de idoneidad exigidas para dichos cargos según cláusulas del Reglamento del Régimen de los Concursos para el Acceso al Empleo Público de la Municipalidad;\nQue en tal sentido, corresponde así mismo la aceptación de las Bases de dicho concurso, las cuales acompañan el presente decreto;\nPor todo ello, en uso de las facultades que me son propias;\nD E C R E T O\nARTICULO 1ro.:\nProcédase al llamado a Concurso Publico General  el día 01 de Diciembre de 2020, para cubrir ocho (8) cargos de la Planta Permanente, a saber: cinco (5)  Personal Obrero, uno (1)  Personal de  Servicio,  y dos (2) Personal de Administración, según el marco de la Ordenanza Nº 2667/2020, de acuerdo a lo expuesto en el considerando.-\nARTICULO 2do.:\nApruébese las Bases del presente  concurso, las cuales se detallan en el  Anexo\nI que acompaña el presente el presente decreto.-\nARTICULO 3ro.:\nEstablecese el Comité de Selección, el cual está integrada por el Director de Recursos Humanos,  Personal Administrativo de la Dirección  de Recursos Humanos y de la Secretaria de Infraestructura, Planificación Urbana y Medio Ambiente.-\nARTICULO 4to.:\nEl presente Decreto será refrendado por la Secretaria General de Gobierno y el Secretario de Hacienda y Finanzas.-\nARTICULO 5to.:\nComuníquese, Publíquese, Regístrese y Cumplido, Archívese.-\nFIRMADO:        ING. JAVIER IGUACEL                        = INTENDENTE MUNICIPAL\nFERNANDA ASTORINO HURTADO     = SEC.\nGRAL. DE GOBIERNO\nFRANCISCO PIGRETTI                        = SEC. DE HACIENDA Y FINANZAS\nAnexos\nCONCURSO\nREGLAMENTACION DEL CONCURSO PUBLICO EMPLEO MUNICIPAL\nDESCARGAR\n"
}