{
  "number": "51º",
  "date": "12/11/2018",
  "description": "51º de Veinticinco de Mayo",
  "link": "/bulletins/1600",
  "status": "completed",
  "fullText": "\n[DOC 1]\nBoletines/Veinticinco de Mayo\nDecreto Nº307/18\nDecreto Nº 307/18\nVeinticinco de Mayo, 07/05/2018\nVisto\nel expediente N° 4118-01463/2018; y\nConsiderando\nQue a fs.1 se presenta el Secretario de Políticas Sociales y Sanitarias, solicitando se declare de\nInterés Municipal\nel\nProyecto Maestros Comunitarios: “Rodolfo Walsh”\n, que será llevado a cabo los días lunes, miércoles y viernes en las siguientes dependencias: C.A.P.S. B. Villa Obrera, B. Verón y B. San Vicente, Casa del Niño “San Miguel Arcángel”, Delegación Del Valle, Delegación Valdés, Delegación Norberto de la Riestra y Club Atlético Defensores de Plaza Italia;\nQue los\nMaestros Comunitarios\nacompañan a cada uno de los niños en el proceso de aprendizaje, brindando las herramientas necesarias  para que puedan asumir las responsabilidades que les tocan;\nQue el objetivo de este proyecto es generar situaciones que estimulen a los alumnos generando el deseo de aprender;\nQue dada la importancia del mismo se estima procedente la declaración de Interés Municipal;\nPor ello,\nEl Intendente de 25 de Mayo decreta\nArtículo 1º)\n:\nDeclarar de\nInterés Municipal\nel\nProyecto Maestros Comunitarios: “Rodolfo Walsh”\n, según constancias obrantes en el expediente N° 4118-01463/2018.\nArtículo 2º)\n:\nBrindar total apoyo y la más amplia difusión\nArtículo 3º)\n:\nRefrendar por el Secretario de Políticas Sociales y Sanitarias y el Secretario de Coordinación y Gestión Pública.\nArtículo 4º)\n:\nRegistrar, comunicar y archivar.\n\n[DOC 2]\nBoletines/Veinticinco de Mayo\nDecreto Nº308/18\nDecreto Nº 308/18\nVeinticinco de Mayo, 08/05/2018\nVisto\nel expediente N° 4118-01461/2018; y\nConsiderando\nQue a fs.1 se presenta el Secretario de Políticas Sociales y Sanitarias, solicitando se declare de\nInterés Municipal\nel\nProyecto Madres Adolescentes “De corazones y vientres”\n, que será llevado a cabo a partir del mes de abril y hasta diciembre del corriente año con uno o dos encuentros al mes en las instalaciones del Jardín Maternal “Arco Iris”;\nQue la maternidad/paternidad en la temprana juventud aparece como un fenómeno de alta complejidad determinado entre otros, por factores socio-económicos;\nQue el objetivo de este proyecto es acompañar a los padres adolescentes en la construcción de sus emociones vinculadas a la nueva experiencia, además de brindarles educación sobre sexualidad y reproducción;\nQue dada la importancia del mismo se estima procedente la declaración de Interés Municipal;\nPor ello,\nEl Intendente Municipal de Mayo decreta\nArtículo 1º)\n:\nDeclarar de de\nInterés Municipal\nel\nProyecto Madres Adolescentes “De corazones y vientres”\n, según constancias obrantes en el expediente N° 4118-01461/2018.\nArtículo 2º)\n:\nBrindar total apoyo y la más amplia difusión\nArtículo 3º)\n:\nRefrendar por el Secretario de Políticas Sociales y Sanitarias y el Secretario de Coordinación y Gestión Pública.\nArtículo 4º)\n:\nRegistrar, comunicar y archivar.\n\n[DOC 3]\nBoletines/Veinticinco de Mayo\nDecreto Nº309/18\nDecreto Nº 309/18\nVeinticinco de Mayo, 08/05/2018\nVisto\nel expediente N° 4118-01322/2018; y\nConsiderando\nQue a fs.1 del expediente citado, consta nota de la Secretaría de Políticas Sociales y Sanitarias, solicitando subsidios varios por emergencia habitacional, socio-económica y salud, para las personas que se detallan a continuación;\nVELA Roberto Gabriel, D.N.I. N° 17.520.682 (por salud);\nGUTIERREZ Joana Elizabeth, D.N.I. N° 37.900.864 (por emergencia habitacional);\nROBLEDO Claudia Marcela, D.N.I. N° 18.760.372 (por emergencia socio-económica);\nILUNDAIN María Delia, D.N.I. N° 29.850.308 (por emergencia socio-económica);\nPRADO Mirta Itatí, D.N.I. N° 28.385.988 (por emergencia socio-económica);\nILUNDAIN Anahí Soledad, D.N.I. N° 30.643.146 (por emergencia habitacional);\nQue fs.16 se autoriza al Sr. VELA Roberto Gabriel la suma de $ 36.000,00, a la Sra. GUTIERREZ Joana Elizabeth la suma de $ 27.000,00, a la Sra. ROBLEDO Claudia Marcela la suma de $ 4.000,00, a la Sra. ILUNDAIN María Delia la suma de $ 3.500,00, a la Sra. PRADO Mirta Itatí la suma de $ 2.700,00 y a la Sra. ILUNDAIN Anahí Soledad la suma de $ 7.000,00, por única vez;\nQue a fs.17, la Contaduría informa la imputación presupuestaria del caso,\nPor ello,\nEl Intendente Municipal de 25 de Mayo decreta\nArtículo 1º)\n:\nOtorgar en concepto de subsidio al Sr. VELA Roberto Gabriel la suma de $ 36.000,00, a la Sra. GUTIERREZ Joana Elizabeth la suma de $ 27.000,00, a la Sra. ROBLEDO Claudia Marcela la suma de $ 4.000,00, a la Sra. ILUNDAIN María Delia la suma de $ 3.500,00, a la Sra. PRADO Mirta Itatí la suma de $ 2.700,00 y a la Sra. ILUNDAIN Anahí Soledad la suma de $ 7.000,00; por única vez; por los motivos expuestos en los considerandos del presente decreto y según constancias obrantes en el expediente Nº 4118-01322/2018.\nArtículo 2º)\n:\nImputar la erogación que demande su cumplimiento a la partida: 1110120000-61-41-110-5000-5100-5140-5141- AYUDA SOCIAL A PERSONAS.\nArtículo 3º)\n:\nRefrendar por el Secretario de Políticas Sociales y Sanitarias y el Secretario de Coordinación y Gestión Pública.\nArtículo 4º)\n:\nRegistrar, comunicar y archivar.\n\n[DOC 4]\nBoletines/Veinticinco de Mayo\nDecreto Nº310/18\nDecreto Nº 310/18\nVeinticinco de Mayo, 08/05/2018\nVisto\nLa nota presentada por el Círculo de Amigos de Boca Juniors Peña “Silvio Marzolini”, que lleva el N° 4118-01472/2018, solicitando su reconocimiento como Entidad de Bien Público Municipal;\nQue obra en las actuaciones mencionadas toda la documentación necesaria para efectuar el trámite requerido;\nPor ello,\nConsiderando\nLa nota presentada por el Círculo de Amigos de Boca Juniors Peña “Silvio Marzolini”, que lleva el N° 4118-01472/2018, solicitando su reconocimiento como Entidad de Bien Público Municipal;\nQue obra en las actuaciones mencionadas toda la documentación necesaria para efectuar el trámite requerido;\nPor ello,\nEl Intendente Municipal de 25 de Mayo decreta\nArtículo 1º)\n:\nReconocer como Entidad de Bien Público Municipal al Círculo de Amigos de Boca Juniors Peña “Silvio Marzolini”.\nArtículo 2º)\n:\nProceder a su registro con el N° 362.\nArtículo 3º)\n:\nRefrendar por el Secretario de Gobierno y el Secretario de Coordinación y Gestión Pública.\nArtículo 4º)\n:\nRegistrar, comunicar y archivar.\n\n[DOC 5]\nBoletines/Veinticinco de Mayo\nDecreto Nº311/18\nDecreto Nº 311/18\nVeinticinco de Mayo, 08/05/2018\nVisto\nel expediente N° 4118-01289/2018; y\nConsiderando\nQue a fs. 1 del expediente citado, consta nota del Secretario de Cultura, Deportes y Juventud, solicitando un subsidio para las siguientes instituciones:\nClub A. Alumni\npor representar al ganador del concurso\n“La voz de 25 Edición 2018”\nCasa del Niño “San Miguel Arcángel”\npor representar al segundo lugar del concurso\n“La voz de 25 Edición 2018”\nClub A. Defensores de Plaza España\npor representar a la pareja ganadora del concurso\n“25 Baila Edición 2018”\nPeña de Boca Junios “Silvio Marzolini”\npor representar a la pareja en segundo lugar en el concurso\n“25 Baila Edición 2018”\n;\nQue a fs.2 se autoriza la suma de $ 7.000,00 para el\nClub A. Alumni\n, la suma de $ 3.000,00 para la\nCasa del Niño “San Miguel Arcángel”,\nla suma de $ 7.000,00 para el\nClub Atlético Defensores de Plaza España\ny la suma de $ 3.000,00 para la\nPeña de Boca Junios “Silvio Marzolini”\n, por única vez;\nQue a fs.4, la Contaduría informa la imputación presupuestaria del caso;\nPor ello,\nEl Intendente Municipal de 25 de Mayo decreta\nArtículo 1º)\n:\nOtorgar un subsidio por única vez, a las siguientes instituciones, por acompañar a los ganadores  de los concursos\n“La Voz de 25 Edición 2018”\ny\n“ 25 Baila Edición 2018”\n,\nde acuerdo al siguiente detalle:\nClub A. Alumni\n- $ 7.000,00 (PESOS SIETE MIL)\nCasa del Niño “San Miguel Arcángel”\n- $ 3.000,00 (PESOS TRES MIL)\nClub A. Defensores de Plaza España\n- $ 7.000,00 (PESOS SIETE MIL)\nPeña de Boca Junios “Silvio Marzolini”\n- $ 3.000,00 (PESOS TRES MIL),\npor los motivos expuestos en los considerandos del presente decreto y según constancias obrantes en el expediente Nº 4118-01289/2018.\nArtículo 2º)\n:\nImputar la erogación que demande su cumplimiento a la partida: 1110101000-2-01.01.00-5000-5100-5170-110- TESORERO MUNICIPAL.\nArtículo 3º)\n:\nRefrendar por el Secretario de Cultura, Juventud y Deporte y el Secretario de  Coordinación y Gestión Pública.\nArtículo 4º)\n:\nRegistrar, comunicar y archivar.\n\n[DOC 6]\nBoletines/Veinticinco de Mayo\nDecreto Nº312/18\nDecreto Nº 312/18\nVeinticinco de Mayo, 08/05/2018\nVisto\nlo dispuesto en los artículos 178º y 181º de la Ley Orgánica de las Municipalidades;     la Ordenanza N° 3316/2017 y;\nConsiderando\nQue es necesario a los efectos de mantener la funcionalidad de la administración en el ámbito jerárquico y de que el Intendente Municipal cuente en forma inmediata con los auxiliares que la ley establece, designar al Ing. Carlos Jesús THOMPSON con D.N.I. N° 21.993.464 como Directos de Asuntos Agrarios, a partir del 1° de mayo del corriente año;\nPor ello,\nEl Intendente Municipal de 25 de Mayo decreta\nArtículo 1º):\nDesignar al Ing. Carlos Jesús THOMPSON con D.N.I. N° 21.993.464 como Director de Asuntos Agrarios, a partir del 1° de mayo de 2018, a efectos de mantener la funcionalidad de la administración en el ámbito jerárquico e integrar el gabinete municipal según lo establecido  en la Ordenanza N° 3316/2017.\nArtículo 2º):\nImputar la erogación que demande su cumplimiento a la siguiente partida presupuestaria: 1110111700-53-16.00.00-16.01.00-110-1000-1110-1112- PERSONAL JERARQUICO.\nArtículo 3º):\nRefrendar por la Secretaria de Producción y el Secretario de Coordinación y Gestión Pública.\nArtículo 4º):\nComunicar  a quienes corresponda,  dar al Registro de Decretos y oportunamente archivar.\n"
}